pysman/__init__.py
pysman/service_manager.py
pysman-0.2.0.dist-info/licenses/LICENSE
pysman-0.2.0.dist-info/METADATA
pysman-0.2.0.dist-info/WHEEL
pysman-0.2.0.dist-info/top_level.txt
pysman-0.2.0.dist-info/RECORD
