Metadata-Version: 2.4
Name: pysman
Version: 0.2.0
Summary: Lightweight Service Manager for Python projects
Author-email: busychild77 <noemail@noemail.com>
License:                     GNU GENERAL PUBLIC LICENSE
Project-URL: Homepage, https://github.com/noviplex/PySMan
Project-URL: Issues, https://github.com/noviplex/PySMan/issues
Classifier: Programming Language :: Python :: 3
Classifier: Operating System :: OS Independent
Requires-Python: >=3.7
License-File: LICENSE
Dynamic: license-file
